.testr.conf
CONTRIBUTING.rst
HACKING.rst
LICENSE
MANIFEST.in
README.rst
__init__.py
babel.cfg
openstack-common.conf
requirements.txt
setup.cfg
setup.py
test-requirements.txt
tox.ini
doc/source/conf.py
doc/source/contributing.rst
doc/source/index.rst
doc/source/installation.rst
doc/source/readme.rst
doc/source/usage.rst
etc/policy.json
networking_brocade/__init__.py
networking_brocade.egg-info/PKG-INFO
networking_brocade.egg-info/SOURCES.txt
networking_brocade.egg-info/dependency_links.txt
networking_brocade.egg-info/not-zip-safe
networking_brocade.egg-info/pbr.json
networking_brocade.egg-info/requires.txt
networking_brocade.egg-info/top_level.txt
networking_brocade/mlx/__init__.py
networking_brocade/mlx/ml2/__init__.py
networking_brocade/mlx/ml2/commands.py
networking_brocade/mlx/ml2/connector_factory.py
networking_brocade/mlx/ml2/device_connector.py
networking_brocade/mlx/ml2/ssh_connector.py
networking_brocade/mlx/ml2/telnet_connector.py
networking_brocade/mlx/ml2/fi_ni/__init__.py
networking_brocade/mlx/ml2/fi_ni/brcd_config.py
networking_brocade/mlx/ml2/fi_ni/driver_factory.py
networking_brocade/mlx/ml2/fi_ni/fi_driver.py
networking_brocade/mlx/ml2/fi_ni/fi_ni_driver.py
networking_brocade/mlx/ml2/fi_ni/mechanism_brocade_fi_ni.py
networking_brocade/mlx/ml2/fi_ni/ni_driver.py
networking_brocade/mlx/services/__init__.py
networking_brocade/mlx/services/l3_router/__init__.py
networking_brocade/mlx/services/l3_router/brocade/__init__.py
networking_brocade/mlx/services/l3_router/brocade/l3_router_plugin.py
networking_brocade/mlx/tests/__init__.py
networking_brocade/mlx/tests/unit/__init__.py
networking_brocade/mlx/tests/unit/ml2/__init__.py
networking_brocade/mlx/tests/unit/ml2/drivers/__init__.py
networking_brocade/mlx/tests/unit/ml2/drivers/brocade/__init__.py
networking_brocade/mlx/tests/unit/ml2/drivers/brocade/test_brocade_fi_ni_mechanism_driver.py
networking_brocade/mlx/tests/unit/services/__init__.py
networking_brocade/mlx/tests/unit/services/l3_router/__init__.py
networking_brocade/mlx/tests/unit/services/l3_router/brocade/__init__.py
networking_brocade/mlx/tests/unit/services/l3_router/brocade/test_l3_router_plugin.py
networking_brocade/test_discover/__init__.py
networking_brocade/test_discover/test_discover.py
